__init__.py
ir.py
log.py
toks.py
wrlparser.py
ply/__init__.py
ply/lex.py
ply/yacc.py
wrlparser-1.0.dist-info/LICENSE
wrlparser-1.0.dist-info/METADATA
wrlparser-1.0.dist-info/WHEEL
wrlparser-1.0.dist-info/top_level.txt
wrlparser-1.0.dist-info/RECORD
