Metadata-Version: 2.1
Name: wrlparser
Version: 1.0
Summary: A VRML (.wrl) parser library
Author-email: Clément Chaine <cc.chaine@free.fr>
License: GNU GENERAL PUBLIC LICENSE
Project-URL: Homepage, https://github.com/cchaine/wrlparser
Project-URL: Bug Tracker, https://github.com/cchaine/wrlparser/issues
Classifier: Programming Language :: Python :: 3
Classifier: License :: OSI Approved :: GNU General Public License v3 (GPLv3)
Classifier: Operating System :: OS Independent
Requires-Python: >=3.7
License-File: LICENSE
Requires-Dist: rich
